{
    "index": "DIV1500567296.76", 
    "top": 139, 
    "id": "sogou_vr_70075002_wrap_0", 
    "width": 550, 
    "tag": "DIV", 
    "leaves": [
        {
            "top": 139, 
            "id": "", 
            "width": 550, 
            "tag": "H3", 
            "leaves": [
                {
                    "top": 143, 
                    "id": "sogou_vr_70075002_title_0", 
                    "width": 304, 
                    "tag": "A", 
                    "leaves": [
                        {
                            "top": 143, 
                            "id": "", 
                            "width": 32, 
                            "tag": "EM", 
                            "leaves": [], 
                            "height": 17, 
                            "class": "", 
                            "left": 121
                        }, 
                        {
                            "top": 143, 
                            "id": "", 
                            "width": 53, 
                            "tag": "EM", 
                            "leaves": [], 
                            "height": 17, 
                            "class": "", 
                            "left": 190
                        }
                    ], 
                    "height": 17, 
                    "class": "", 
                    "left": 121
                }, 
                {
                    "top": 144, 
                    "id": "sogou_vr_70075002_officalicon_0", 
                    "width": 32, 
                    "tag": "SPAN", 
                    "leaves": [], 
                    "height": 16, 
                    "class": "vr-authico", 
                    "left": 428
                }
            ], 
            "height": 26, 
            "class": "vrTitle", 
            "left": 121
        }, 
        {
            "top": 165, 
            "id": "", 
            "width": 550, 
            "tag": "DIV", 
            "leaves": [
                {
                    "top": 166, 
                    "id": "", 
                    "width": 550, 
                    "tag": "DIV", 
                    "leaves": [
                        {
                            "top": 169, 
                            "id": "sogou_vr_70075002_pic_0", 
                            "width": 122, 
                            "tag": "A", 
                            "leaves": [
                                {
                                    "top": 170, 
                                    "id": "", 
                                    "width": 120, 
                                    "tag": "IMG", 
                                    "leaves": [], 
                                    "height": 90, 
                                    "class": "", 
                                    "left": 122
                                }
                            ], 
                            "height": 92, 
                            "class": "pic-box", 
                            "left": 121
                        }, 
                        {
                            "top": 166, 
                            "id": "", 
                            "width": 418, 
                            "tag": "DIV", 
                            "leaves": [
                                {
                                    "top": 166, 
                                    "id": "", 
                                    "width": 418, 
                                    "tag": "P", 
                                    "leaves": [], 
                                    "height": 40, 
                                    "class": "info-txt", 
                                    "left": 253
                                }, 
                                {
                                    "top": 207, 
                                    "id": "", 
                                    "width": 418, 
                                    "tag": "DIV", 
                                    "leaves": [
                                        {
                                            "top": 209, 
                                            "id": "", 
                                            "width": 139, 
                                            "tag": "SPAN", 
                                            "leaves": [
                                                {
                                                    "top": 211, 
                                                    "id": "", 
                                                    "width": 14, 
                                                    "tag": "I", 
                                                    "leaves": [], 
                                                    "height": 12, 
                                                    "class": "", 
                                                    "left": 253
                                                }
                                            ], 
                                            "height": 15, 
                                            "class": "", 
                                            "left": 253
                                        }, 
                                        {
                                            "top": 209, 
                                            "id": "", 
                                            "width": 136, 
                                            "tag": "SPAN", 
                                            "leaves": [
                                                {
                                                    "top": 211, 
                                                    "id": "", 
                                                    "width": 14, 
                                                    "tag": "I", 
                                                    "leaves": [], 
                                                    "height": 12, 
                                                    "class": "i2", 
                                                    "left": 402
                                                }
                                            ], 
                                            "height": 15, 
                                            "class": "", 
                                            "left": 402
                                        }
                                    ], 
                                    "height": 20, 
                                    "class": "p-num", 
                                    "left": 253
                                }, 
                                {
                                    "top": 233, 
                                    "id": "", 
                                    "width": 418, 
                                    "tag": "DIV", 
                                    "leaves": [
                                        {
                                            "top": 233, 
                                            "id": "sogou_vr_70075002_guanwang_0", 
                                            "width": 72, 
                                            "tag": "A", 
                                            "leaves": [], 
                                            "height": 30, 
                                            "class": "btn-bg-ff6949", 
                                            "left": 253
                                        }
                                    ], 
                                    "height": 30, 
                                    "class": "btn-box", 
                                    "left": 253
                                }
                            ], 
                            "height": 97, 
                            "class": "game-info", 
                            "left": 253
                        }
                    ], 
                    "height": 97, 
                    "class": "game-box1", 
                    "left": 121
                }, 
                {
                    "top": 273, 
                    "id": "", 
                    "width": 550, 
                    "tag": "DIV", 
                    "leaves": [
                        {
                            "top": 273, 
                            "id": "", 
                            "width": 550, 
                            "tag": "UL", 
                            "leaves": [
                                {
                                    "top": 273, 
                                    "id": "", 
                                    "width": 72, 
                                    "tag": "LI", 
                                    "leaves": [
                                        {
                                            "top": 273, 
                                            "id": "", 
                                            "width": 72, 
                                            "tag": "A", 
                                            "leaves": [], 
                                            "height": 32, 
                                            "class": "", 
                                            "left": 121
                                        }
                                    ], 
                                    "height": 32, 
                                    "class": "", 
                                    "left": 121
                                }, 
                                {
                                    "top": 273, 
                                    "id": "", 
                                    "width": 72, 
                                    "tag": "LI", 
                                    "leaves": [
                                        {
                                            "top": 273, 
                                            "id": "", 
                                            "width": 72, 
                                            "tag": "A", 
                                            "leaves": [], 
                                            "height": 32, 
                                            "class": "", 
                                            "left": 193
                                        }
                                    ], 
                                    "height": 32, 
                                    "class": "cur", 
                                    "left": 193
                                }
                            ], 
                            "height": 32, 
                            "class": "tab-vr-lis", 
                            "left": 121
                        }
                    ], 
                    "height": 32, 
                    "class": "tab-vr-tit", 
                    "left": 121
                }, 
                {
                    "top": 315, 
                    "id": "", 
                    "width": 550, 
                    "tag": "DIV", 
                    "leaves": [
                        {
                            "top": 315, 
                            "id": "", 
                            "width": 550, 
                            "tag": "DIV", 
                            "leaves": [
                                {
                                    "top": 315, 
                                    "id": "", 
                                    "width": 575, 
                                    "tag": "UL", 
                                    "leaves": [
                                        {
                                            "top": 315, 
                                            "id": "", 
                                            "width": 90, 
                                            "tag": "LI", 
                                            "leaves": [
                                                {
                                                    "top": 315, 
                                                    "id": "sogou_vr_70075002_game-0_0", 
                                                    "width": 90, 
                                                    "tag": "A", 
                                                    "leaves": [
                                                        {
                                                            "top": 315, 
                                                            "id": "", 
                                                            "width": 90, 
                                                            "tag": "IMG", 
                                                            "leaves": [], 
                                                            "height": 120, 
                                                            "class": "", 
                                                            "left": 121
                                                        }
                                                    ], 
                                                    "height": 120, 
                                                    "class": "video-list-pic", 
                                                    "left": 121
                                                }, 
                                                {
                                                    "top": 439, 
                                                    "id": "", 
                                                    "width": 90, 
                                                    "tag": "P", 
                                                    "leaves": [
                                                        {
                                                            "top": 439, 
                                                            "id": "sogou_vr_70075002_game-0_0", 
                                                            "width": 90, 
                                                            "tag": "A", 
                                                            "leaves": [], 
                                                            "height": 16, 
                                                            "class": "", 
                                                            "left": 121
                                                        }
                                                    ], 
                                                    "height": 16, 
                                                    "class": "one-ov", 
                                                    "left": 121
                                                }
                                            ], 
                                            "height": 141, 
                                            "class": "", 
                                            "left": 121
                                        }, 
                                        {
                                            "top": 315, 
                                            "id": "", 
                                            "width": 90, 
                                            "tag": "LI", 
                                            "leaves": [
                                                {
                                                    "top": 315, 
                                                    "id": "sogou_vr_70075002_game-1_0", 
                                                    "width": 90, 
                                                    "tag": "A", 
                                                    "leaves": [
                                                        {
                                                            "top": 315, 
                                                            "id": "", 
                                                            "width": 90, 
                                                            "tag": "IMG", 
                                                            "leaves": [], 
                                                            "height": 120, 
                                                            "class": "", 
                                                            "left": 236
                                                        }
                                                    ], 
                                                    "height": 120, 
                                                    "class": "video-list-pic", 
                                                    "left": 236
                                                }, 
                                                {
                                                    "top": 439, 
                                                    "id": "", 
                                                    "width": 90, 
                                                    "tag": "P", 
                                                    "leaves": [
                                                        {
                                                            "top": 439, 
                                                            "id": "sogou_vr_70075002_game-1_0", 
                                                            "width": 90, 
                                                            "tag": "A", 
                                                            "leaves": [], 
                                                            "height": 16, 
                                                            "class": "", 
                                                            "left": 236
                                                        }
                                                    ], 
                                                    "height": 16, 
                                                    "class": "one-ov", 
                                                    "left": 236
                                                }
                                            ], 
                                            "height": 141, 
                                            "class": "", 
                                            "left": 236
                                        }, 
                                        {
                                            "top": 315, 
                                            "id": "", 
                                            "width": 90, 
                                            "tag": "LI", 
                                            "leaves": [
                                                {
                                                    "top": 315, 
                                                    "id": "sogou_vr_70075002_game-2_0", 
                                                    "width": 90, 
                                                    "tag": "A", 
                                                    "leaves": [
                                                        {
                                                            "top": 315, 
                                                            "id": "", 
                                                            "width": 90, 
                                                            "tag": "IMG", 
                                                            "leaves": [], 
                                                            "height": 120, 
                                                            "class": "", 
                                                            "left": 351
                                                        }
                                                    ], 
                                                    "height": 120, 
                                                    "class": "video-list-pic", 
                                                    "left": 351
                                                }, 
                                                {
                                                    "top": 439, 
                                                    "id": "", 
                                                    "width": 90, 
                                                    "tag": "P", 
                                                    "leaves": [
                                                        {
                                                            "top": 439, 
                                                            "id": "sogou_vr_70075002_game-2_0", 
                                                            "width": 90, 
                                                            "tag": "A", 
                                                            "leaves": [], 
                                                            "height": 16, 
                                                            "class": "", 
                                                            "left": 351
                                                        }
                                                    ], 
                                                    "height": 16, 
                                                    "class": "one-ov", 
                                                    "left": 351
                                                }
                                            ], 
                                            "height": 141, 
                                            "class": "", 
                                            "left": 351
                                        }, 
                                        {
                                            "top": 315, 
                                            "id": "", 
                                            "width": 90, 
                                            "tag": "LI", 
                                            "leaves": [
                                                {
                                                    "top": 315, 
                                                    "id": "sogou_vr_70075002_game-3_0", 
                                                    "width": 90, 
                                                    "tag": "A", 
                                                    "leaves": [
                                                        {
                                                            "top": 315, 
                                                            "id": "", 
                                                            "width": 90, 
                                                            "tag": "IMG", 
                                                            "leaves": [], 
                                                            "height": 120, 
                                                            "class": "", 
                                                            "left": 466
                                                        }
                                                    ], 
                                                    "height": 120, 
                                                    "class": "video-list-pic", 
                                                    "left": 466
                                                }, 
                                                {
                                                    "top": 439, 
                                                    "id": "", 
                                                    "width": 90, 
                                                    "tag": "P", 
                                                    "leaves": [
                                                        {
                                                            "top": 439, 
                                                            "id": "sogou_vr_70075002_game-3_0", 
                                                            "width": 90, 
                                                            "tag": "A", 
                                                            "leaves": [], 
                                                            "height": 16, 
                                                            "class": "", 
                                                            "left": 466
                                                        }
                                                    ], 
                                                    "height": 16, 
                                                    "class": "one-ov", 
                                                    "left": 466
                                                }
                                            ], 
                                            "height": 141, 
                                            "class": "", 
                                            "left": 466
                                        }, 
                                        {
                                            "top": 315, 
                                            "id": "", 
                                            "width": 90, 
                                            "tag": "LI", 
                                            "leaves": [
                                                {
                                                    "top": 315, 
                                                    "id": "sogou_vr_70075002_game-4_0", 
                                                    "width": 90, 
                                                    "tag": "A", 
                                                    "leaves": [
                                                        {
                                                            "top": 315, 
                                                            "id": "", 
                                                            "width": 90, 
                                                            "tag": "IMG", 
                                                            "leaves": [], 
                                                            "height": 120, 
                                                            "class": "", 
                                                            "left": 581
                                                        }
                                                    ], 
                                                    "height": 120, 
                                                    "class": "video-list-pic", 
                                                    "left": 581
                                                }, 
                                                {
                                                    "top": 439, 
                                                    "id": "", 
                                                    "width": 90, 
                                                    "tag": "P", 
                                                    "leaves": [
                                                        {
                                                            "top": 439, 
                                                            "id": "sogou_vr_70075002_game-4_0", 
                                                            "width": 90, 
                                                            "tag": "A", 
                                                            "leaves": [], 
                                                            "height": 16, 
                                                            "class": "", 
                                                            "left": 581
                                                        }
                                                    ], 
                                                    "height": 16, 
                                                    "class": "one-ov", 
                                                    "left": 581
                                                }
                                            ], 
                                            "height": 141, 
                                            "class": "", 
                                            "left": 581
                                        }
                                    ], 
                                    "height": 141, 
                                    "class": "video-list1 video-list2", 
                                    "left": 96
                                }, 
                                {
                                    "top": 460, 
                                    "id": "", 
                                    "width": 550, 
                                    "tag": "P", 
                                    "leaves": [
                                        {
                                            "top": 460, 
                                            "id": "sogou_vr_70075002_moreLink_0", 
                                            "width": 67, 
                                            "tag": "A", 
                                            "leaves": [], 
                                            "height": 22, 
                                            "class": "", 
                                            "left": 121
                                        }
                                    ], 
                                    "height": 22, 
                                    "class": "moreLink", 
                                    "left": 121
                                }
                            ], 
                            "height": 167, 
                            "class": "tab-con", 
                            "left": 121
                        }
                    ], 
                    "height": 169, 
                    "class": "video-box", 
                    "left": 121
                }, 
                {
                    "top": 488, 
                    "id": "sogou_vr_70075002_zhubo_0", 
                    "width": 550, 
                    "tag": "DIV", 
                    "leaves": [
                        {
                            "top": 489, 
                            "id": "", 
                            "width": 550, 
                            "tag": "H4", 
                            "leaves": [], 
                            "height": 32, 
                            "class": "", 
                            "left": 121
                        }, 
                        {
                            "top": 521, 
                            "id": "", 
                            "width": 567, 
                            "tag": "UL", 
                            "leaves": [
                                {
                                    "top": 521, 
                                    "id": "", 
                                    "width": 77, 
                                    "tag": "LI", 
                                    "leaves": [
                                        {
                                            "top": 521, 
                                            "id": "sogou_vr_70075002_zhubo-thumb-0_0", 
                                            "width": 77, 
                                            "tag": "A", 
                                            "leaves": [
                                                {
                                                    "top": 521, 
                                                    "id": "", 
                                                    "width": 75, 
                                                    "tag": "IMG", 
                                                    "leaves": [], 
                                                    "height": 75, 
                                                    "class": "", 
                                                    "left": 121
                                                }, 
                                                {
                                                    "top": 576, 
                                                    "id": "", 
                                                    "width": 75, 
                                                    "tag": "P", 
                                                    "leaves": [], 
                                                    "height": 20, 
                                                    "class": "txt-bg", 
                                                    "left": 121
                                                }, 
                                                {
                                                    "top": 576, 
                                                    "id": "", 
                                                    "width": 75, 
                                                    "tag": "P", 
                                                    "leaves": [], 
                                                    "height": 20, 
                                                    "class": "pic-txt", 
                                                    "left": 121
                                                }
                                            ], 
                                            "height": 77, 
                                            "class": "video-list-pic", 
                                            "left": 121
                                        }, 
                                        {
                                            "top": 602, 
                                            "id": "", 
                                            "width": 77, 
                                            "tag": "P", 
                                            "leaves": [
                                                {
                                                    "top": 602, 
                                                    "id": "sogou_vr_70075002_zhubo-title-0_0", 
                                                    "width": 77, 
                                                    "tag": "A", 
                                                    "leaves": [], 
                                                    "height": 16, 
                                                    "class": "", 
                                                    "left": 121
                                                }
                                            ], 
                                            "height": 16, 
                                            "class": "one-ov", 
                                            "left": 121
                                        }, 
                                        {
                                            "top": 619, 
                                            "id": "", 
                                            "width": 77, 
                                            "tag": "P", 
                                            "leaves": [], 
                                            "height": 16, 
                                            "class": "one-ov", 
                                            "left": 121
                                        }
                                    ], 
                                    "height": 115, 
                                    "class": "", 
                                    "left": 121
                                }, 
                                {
                                    "top": 521, 
                                    "id": "", 
                                    "width": 77, 
                                    "tag": "LI", 
                                    "leaves": [
                                        {
                                            "top": 521, 
                                            "id": "sogou_vr_70075002_zhubo-thumb-1_0", 
                                            "width": 77, 
                                            "tag": "A", 
                                            "leaves": [
                                                {
                                                    "top": 521, 
                                                    "id": "", 
                                                    "width": 75, 
                                                    "tag": "IMG", 
                                                    "leaves": [], 
                                                    "height": 75, 
                                                    "class": "", 
                                                    "left": 215
                                                }, 
                                                {
                                                    "top": 576, 
                                                    "id": "", 
                                                    "width": 75, 
                                                    "tag": "P", 
                                                    "leaves": [], 
                                                    "height": 20, 
                                                    "class": "txt-bg", 
                                                    "left": 215
                                                }, 
                                                {
                                                    "top": 576, 
                                                    "id": "", 
                                                    "width": 75, 
                                                    "tag": "P", 
                                                    "leaves": [], 
                                                    "height": 20, 
                                                    "class": "pic-txt", 
                                                    "left": 215
                                                }
                                            ], 
                                            "height": 77, 
                                            "class": "video-list-pic", 
                                            "left": 215
                                        }, 
                                        {
                                            "top": 602, 
                                            "id": "", 
                                            "width": 77, 
                                            "tag": "P", 
                                            "leaves": [
                                                {
                                                    "top": 602, 
                                                    "id": "sogou_vr_70075002_zhubo-title-1_0", 
                                                    "width": 77, 
                                                    "tag": "A", 
                                                    "leaves": [], 
                                                    "height": 16, 
                                                    "class": "", 
                                                    "left": 215
                                                }
                                            ], 
                                            "height": 16, 
                                            "class": "one-ov", 
                                            "left": 215
                                        }, 
                                        {
                                            "top": 619, 
                                            "id": "", 
                                            "width": 77, 
                                            "tag": "P", 
                                            "leaves": [], 
                                            "height": 16, 
                                            "class": "one-ov", 
                                            "left": 215
                                        }
                                    ], 
                                    "height": 115, 
                                    "class": "", 
                                    "left": 215
                                }, 
                                {
                                    "top": 521, 
                                    "id": "", 
                                    "width": 77, 
                                    "tag": "LI", 
                                    "leaves": [
                                        {
                                            "top": 521, 
                                            "id": "sogou_vr_70075002_zhubo-thumb-2_0", 
                                            "width": 77, 
                                            "tag": "A", 
                                            "leaves": [
                                                {
                                                    "top": 521, 
                                                    "id": "", 
                                                    "width": 75, 
                                                    "tag": "IMG", 
                                                    "leaves": [], 
                                                    "height": 75, 
                                                    "class": "", 
                                                    "left": 309
                                                }, 
                                                {
                                                    "top": 576, 
                                                    "id": "", 
                                                    "width": 75, 
                                                    "tag": "P", 
                                                    "leaves": [], 
                                                    "height": 20, 
                                                    "class": "txt-bg", 
                                                    "left": 309
                                                }, 
                                                {
                                                    "top": 576, 
                                                    "id": "", 
                                                    "width": 75, 
                                                    "tag": "P", 
                                                    "leaves": [], 
                                                    "height": 20, 
                                                    "class": "pic-txt", 
                                                    "left": 309
                                                }
                                            ], 
                                            "height": 77, 
                                            "class": "video-list-pic", 
                                            "left": 309
                                        }, 
                                        {
                                            "top": 602, 
                                            "id": "", 
                                            "width": 77, 
                                            "tag": "P", 
                                            "leaves": [
                                                {
                                                    "top": 602, 
                                                    "id": "sogou_vr_70075002_zhubo-title-2_0", 
                                                    "width": 77, 
                                                    "tag": "A", 
                                                    "leaves": [], 
                                                    "height": 16, 
                                                    "class": "", 
                                                    "left": 309
                                                }
                                            ], 
                                            "height": 16, 
                                            "class": "one-ov", 
                                            "left": 309
                                        }, 
                                        {
                                            "top": 619, 
                                            "id": "", 
                                            "width": 77, 
                                            "tag": "P", 
                                            "leaves": [], 
                                            "height": 16, 
                                            "class": "one-ov", 
                                            "left": 309
                                        }
                                    ], 
                                    "height": 115, 
                                    "class": "", 
                                    "left": 309
                                }, 
                                {
                                    "top": 521, 
                                    "id": "", 
                                    "width": 77, 
                                    "tag": "LI", 
                                    "leaves": [
                                        {
                                            "top": 521, 
                                            "id": "sogou_vr_70075002_zhubo-thumb-3_0", 
                                            "width": 77, 
                                            "tag": "A", 
                                            "leaves": [
                                                {
                                                    "top": 521, 
                                                    "id": "", 
                                                    "width": 75, 
                                                    "tag": "IMG", 
                                                    "leaves": [], 
                                                    "height": 75, 
                                                    "class": "", 
                                                    "left": 403
                                                }, 
                                                {
                                                    "top": 576, 
                                                    "id": "", 
                                                    "width": 75, 
                                                    "tag": "P", 
                                                    "leaves": [], 
                                                    "height": 20, 
                                                    "class": "txt-bg", 
                                                    "left": 403
                                                }, 
                                                {
                                                    "top": 576, 
                                                    "id": "", 
                                                    "width": 75, 
                                                    "tag": "P", 
                                                    "leaves": [], 
                                                    "height": 20, 
                                                    "class": "pic-txt", 
                                                    "left": 403
                                                }
                                            ], 
                                            "height": 77, 
                                            "class": "video-list-pic", 
                                            "left": 403
                                        }, 
                                        {
                                            "top": 602, 
                                            "id": "", 
                                            "width": 77, 
                                            "tag": "P", 
                                            "leaves": [
                                                {
                                                    "top": 602, 
                                                    "id": "sogou_vr_70075002_zhubo-title-3_0", 
                                                    "width": 77, 
                                                    "tag": "A", 
                                                    "leaves": [], 
                                                    "height": 16, 
                                                    "class": "", 
                                                    "left": 403
                                                }
                                            ], 
                                            "height": 16, 
                                            "class": "one-ov", 
                                            "left": 403
                                        }, 
                                        {
                                            "top": 619, 
                                            "id": "", 
                                            "width": 77, 
                                            "tag": "P", 
                                            "leaves": [], 
                                            "height": 16, 
                                            "class": "one-ov", 
                                            "left": 403
                                        }
                                    ], 
                                    "height": 115, 
                                    "class": "", 
                                    "left": 403
                                }, 
                                {
                                    "top": 521, 
                                    "id": "", 
                                    "width": 77, 
                                    "tag": "LI", 
                                    "leaves": [
                                        {
                                            "top": 521, 
                                            "id": "sogou_vr_70075002_zhubo-thumb-4_0", 
                                            "width": 77, 
                                            "tag": "A", 
                                            "leaves": [
                                                {
                                                    "top": 521, 
                                                    "id": "", 
                                                    "width": 75, 
                                                    "tag": "IMG", 
                                                    "leaves": [], 
                                                    "height": 75, 
                                                    "class": "", 
                                                    "left": 497
                                                }, 
                                                {
                                                    "top": 576, 
                                                    "id": "", 
                                                    "width": 75, 
                                                    "tag": "P", 
                                                    "leaves": [], 
                                                    "height": 20, 
                                                    "class": "txt-bg", 
                                                    "left": 497
                                                }, 
                                                {
                                                    "top": 576, 
                                                    "id": "", 
                                                    "width": 75, 
                                                    "tag": "P", 
                                                    "leaves": [], 
                                                    "height": 20, 
                                                    "class": "pic-txt", 
                                                    "left": 497
                                                }
                                            ], 
                                            "height": 77, 
                                            "class": "video-list-pic", 
                                            "left": 497
                                        }, 
                                        {
                                            "top": 602, 
                                            "id": "", 
                                            "width": 77, 
                                            "tag": "P", 
                                            "leaves": [
                                                {
                                                    "top": 602, 
                                                    "id": "sogou_vr_70075002_zhubo-title-4_0", 
                                                    "width": 77, 
                                                    "tag": "A", 
                                                    "leaves": [], 
                                                    "height": 16, 
                                                    "class": "", 
                                                    "left": 497
                                                }
                                            ], 
                                            "height": 16, 
                                            "class": "one-ov", 
                                            "left": 497
                                        }, 
                                        {
                                            "top": 619, 
                                            "id": "", 
                                            "width": 77, 
                                            "tag": "P", 
                                            "leaves": [], 
                                            "height": 16, 
                                            "class": "one-ov", 
                                            "left": 497
                                        }
                                    ], 
                                    "height": 115, 
                                    "class": "", 
                                    "left": 497
                                }, 
                                {
                                    "top": 521, 
                                    "id": "", 
                                    "width": 77, 
                                    "tag": "LI", 
                                    "leaves": [
                                        {
                                            "top": 521, 
                                            "id": "sogou_vr_70075002_zhubo-thumb-5_0", 
                                            "width": 77, 
                                            "tag": "A", 
                                            "leaves": [
                                                {
                                                    "top": 521, 
                                                    "id": "", 
                                                    "width": 75, 
                                                    "tag": "IMG", 
                                                    "leaves": [], 
                                                    "height": 75, 
                                                    "class": "", 
                                                    "left": 591
                                                }, 
                                                {
                                                    "top": 576, 
                                                    "id": "", 
                                                    "width": 75, 
                                                    "tag": "P", 
                                                    "leaves": [], 
                                                    "height": 20, 
                                                    "class": "txt-bg", 
                                                    "left": 591
                                                }, 
                                                {
                                                    "top": 576, 
                                                    "id": "", 
                                                    "width": 75, 
                                                    "tag": "P", 
                                                    "leaves": [], 
                                                    "height": 20, 
                                                    "class": "pic-txt", 
                                                    "left": 591
                                                }
                                            ], 
                                            "height": 77, 
                                            "class": "video-list-pic", 
                                            "left": 591
                                        }, 
                                        {
                                            "top": 602, 
                                            "id": "", 
                                            "width": 77, 
                                            "tag": "P", 
                                            "leaves": [
                                                {
                                                    "top": 602, 
                                                    "id": "sogou_vr_70075002_zhubo-title-5_0", 
                                                    "width": 77, 
                                                    "tag": "A", 
                                                    "leaves": [], 
                                                    "height": 16, 
                                                    "class": "", 
                                                    "left": 591
                                                }
                                            ], 
                                            "height": 16, 
                                            "class": "one-ov", 
                                            "left": 591
                                        }, 
                                        {
                                            "top": 619, 
                                            "id": "", 
                                            "width": 77, 
                                            "tag": "P", 
                                            "leaves": [], 
                                            "height": 16, 
                                            "class": "one-ov", 
                                            "left": 591
                                        }
                                    ], 
                                    "height": 115, 
                                    "class": "", 
                                    "left": 591
                                }
                            ], 
                            "height": 115, 
                            "class": "video-list1 anchor-list", 
                            "left": 104
                        }
                    ], 
                    "height": 148, 
                    "class": "anchor-box", 
                    "left": 121
                }, 
                {
                    "top": 640, 
                    "id": "sogou_vr_70075002_gouzai_0", 
                    "width": 550, 
                    "tag": "P", 
                    "leaves": [
                        {
                            "top": 640, 
                            "id": "sogou_vr_70075002_moreLink_0", 
                            "width": 176, 
                            "tag": "A", 
                            "leaves": [
                                {
                                    "top": 642, 
                                    "id": "", 
                                    "width": 16, 
                                    "tag": "I", 
                                    "leaves": [], 
                                    "height": 16, 
                                    "class": "gou-ico", 
                                    "left": 121
                                }
                            ], 
                            "height": 22, 
                            "class": "", 
                            "left": 121
                        }
                    ], 
                    "height": 22, 
                    "class": "moreLink", 
                    "left": 121
                }
            ], 
            "height": 497, 
            "class": "vr-game160427", 
            "left": 121
        }, 
        {
            "top": 664, 
            "id": "", 
            "width": 550, 
            "tag": "DIV", 
            "leaves": [
                {
                    "top": 664, 
                    "id": "", 
                    "width": 162, 
                    "tag": "CITE", 
                    "leaves": [], 
                    "height": 22, 
                    "class": "", 
                    "left": 121
                }
            ], 
            "height": 22, 
            "class": "fb", 
            "left": 121
        }
    ], 
    "height": 547, 
    "class": "vrwrap", 
    "left": 121
}